django_npm_mjs-3.2.1.dist-info/licenses/LICENSE
npm_mjs/__init__.py
npm_mjs/package.json5
npm_mjs/paths.py
npm_mjs/signals.py
npm_mjs/storage.py
npm_mjs/tools.py
npm_mjs/management/__init__.py
npm_mjs/management/commands/__init__.py
npm_mjs/management/commands/collectstatic.py
npm_mjs/management/commands/create_package_json.py
npm_mjs/management/commands/makemessages.py
npm_mjs/management/commands/npm_install.py
npm_mjs/management/commands/rspack.config.template.js
npm_mjs/management/commands/transpile.py
npm_mjs/templatetags/__init__.py
npm_mjs/templatetags/transpile.py
django_npm_mjs-3.2.1.dist-info/METADATA
django_npm_mjs-3.2.1.dist-info/WHEEL
django_npm_mjs-3.2.1.dist-info/top_level.txt
django_npm_mjs-3.2.1.dist-info/RECORD
