Metadata-Version: 2.4
Name: django-npm-mjs
Version: 3.2.1
Summary: A Django package to use npm.js dependencies and transpile ES2015+
Author-email: Johannes Wilm <johannes@fiduswriter.org>
License-Expression: LGPL-3.0-or-later
Project-URL: repository, https://github.com/fiduswriter/django-npm-mjs
Classifier: Environment :: Web Environment
Classifier: Framework :: Django
Classifier: Framework :: Django :: 4.2
Classifier: Framework :: Django :: 5.0
Classifier: Framework :: Django :: 5.1
Classifier: Intended Audience :: Developers
Classifier: Operating System :: OS Independent
Classifier: Programming Language :: Python
Classifier: Programming Language :: Python :: 3.9
Classifier: Programming Language :: Python :: 3.10
Classifier: Programming Language :: Python :: 3.11
Classifier: Programming Language :: Python :: 3.12
Classifier: Programming Language :: Python :: 3.13
Classifier: Topic :: Internet :: WWW/HTTP
Classifier: Topic :: Internet :: WWW/HTTP :: Dynamic Content
License-File: LICENSE
Requires-Dist: Django>=3.2
Requires-Dist: pyjson5==1.6.9
Dynamic: license-file
